pnoise/__init__.py
pnoise/pnoise.py
pnoise-0.2.0.dist-info/LICENSE
pnoise-0.2.0.dist-info/METADATA
pnoise-0.2.0.dist-info/WHEEL
pnoise-0.2.0.dist-info/top_level.txt
pnoise-0.2.0.dist-info/RECORD
