Metadata-Version: 2.1
Name: pnoise
Version: 0.2.0
Summary: Vectorized port of Processing noise() function
Home-page: https://github.com/plottertools/pnoise
Author: Antoine Beyeler
Author-email: abeyeler@ab-ware.com
License: LGPL 2.1
Platform: UNKNOWN
Classifier: License :: OSI Approved :: GNU Lesser General Public License v2 or later (LGPLv2+)
Classifier: Operating System :: OS Independent
Classifier: Programming Language :: Python :: 3
Classifier: Topic :: Multimedia :: Graphics
Classifier: Typing :: Typed
Requires-Python: >=3.6
License-File: LICENSE
